{"id":"ev_3Nl7oGgQqGG8U34r","occurred_at":1364845255,"source":"scheduled_job","object":"event","api_version":"v2","content":{"credit_note":{"id":"TEST-CN-1","customer_id":"3Nl7oGgQqGFprj9","subscription_id":"3Nl7oGgQqGFprj9","reference_invoice_id":"3","type":"refundable","reason_code":"subscription_change","status":"refunded","date":1362253266,"price_type":"tax_exclusive","exchange_rate":1.0,"total":871,"amount_allocated":871,"amount_refunded":0,"amount_available":0,"refunded_at":1364845255,"updated_at":1364845255,"resource_version":1364845255000,"deleted":false,"object":"credit_note","currency_code":"USD","round_off_amount":0,"base_currency_code":"USD","sub_total":871,"line_items":[{"id":"li_3Nl7oGgQqGFzvK3N","date_from":1362253265,"date_to":1364845254,"unit_amount":871,"quantity":1,"is_taxed":false,"tax_amount":0,"object":"line_item","subscription_id":"3Nl7oGgQqGFprj9","amount":871,"description":"Basic - Prorated Credits for 03-Mar-2013 - 02-Apr-2013","entity_type":"plan","entity_id":"basic","tax_exempt_reason":"tax_not_configured","discount_amount":0,"item_level_discount_amount":0}],"taxes":[],"line_item_taxes":[],"line_item_discounts":[],"linked_refunds":[],"allocations":[{"allocated_amount":871,"allocated_at":1364845255,"invoice_id":"6","invoice_date":1364845254,"invoice_status":"payment_due"}]}},"event_type":"credit_note_updated","webhook_status":"not_configured"}